pydantic_tfl_api/__init__.py
pydantic_tfl_api/api_mindmap.mmd
pydantic_tfl_api/class_diagram.mmd
pydantic_tfl_api/py.typed
pydantic_tfl_api/core/__init__.py
pydantic_tfl_api/core/async_client.py
pydantic_tfl_api/core/async_rest_client.py
pydantic_tfl_api/core/client.py
pydantic_tfl_api/core/config.py
pydantic_tfl_api/core/http_client.py
pydantic_tfl_api/core/package_models.py
pydantic_tfl_api/core/response.py
pydantic_tfl_api/core/rest_client.py
pydantic_tfl_api/core/http_backends/__init__.py
pydantic_tfl_api/core/http_backends/async_httpx_client.py
pydantic_tfl_api/core/http_backends/httpx_client.py
pydantic_tfl_api/core/http_backends/requests_client.py
pydantic_tfl_api/endpoints/AccidentStatsClient.py
pydantic_tfl_api/endpoints/AccidentStatsClient_config.py
pydantic_tfl_api/endpoints/AirQualityClient.py
pydantic_tfl_api/endpoints/AirQualityClient_config.py
pydantic_tfl_api/endpoints/BikePointClient.py
pydantic_tfl_api/endpoints/BikePointClient_config.py
pydantic_tfl_api/endpoints/CrowdingClient.py
pydantic_tfl_api/endpoints/CrowdingClient_config.py
pydantic_tfl_api/endpoints/JourneyClient.py
pydantic_tfl_api/endpoints/JourneyClient_config.py
pydantic_tfl_api/endpoints/LiftDisruptionsClient.py
pydantic_tfl_api/endpoints/LiftDisruptionsClient_config.py
pydantic_tfl_api/endpoints/LineClient.py
pydantic_tfl_api/endpoints/LineClient_config.py
pydantic_tfl_api/endpoints/ModeClient.py
pydantic_tfl_api/endpoints/ModeClient_config.py
pydantic_tfl_api/endpoints/OccupancyClient.py
pydantic_tfl_api/endpoints/OccupancyClient_config.py
pydantic_tfl_api/endpoints/PlaceClient.py
pydantic_tfl_api/endpoints/PlaceClient_config.py
pydantic_tfl_api/endpoints/RoadClient.py
pydantic_tfl_api/endpoints/RoadClient_config.py
pydantic_tfl_api/endpoints/SearchClient.py
pydantic_tfl_api/endpoints/SearchClient_config.py
pydantic_tfl_api/endpoints/StopPointClient.py
pydantic_tfl_api/endpoints/StopPointClient_config.py
pydantic_tfl_api/endpoints/VehicleClient.py
pydantic_tfl_api-3.1.0.dist-info/METADATA
pydantic_tfl_api-3.1.0.dist-info/WHEEL
pydantic_tfl_api-3.1.0.dist-info/licenses/LICENSE
pydantic_tfl_api-3.1.0.dist-info/RECORD
