Metadata-Version: 2.4
Name: pydantic-tfl-api
Version: 3.1.0
Summary: A Pydantic-based wrapper for the TfL Unified API https://api-portal.tfl.gov.uk/. Not associated with or endorsed by TfL.
Project-URL: Homepage, https://github.com/mnbf9rca/pydantic_tfl_api
Project-URL: Repository, https://github.com/mnbf9rca/pydantic_tfl_api
Project-URL: Issues, https://github.com/mnbf9rca/pydantic_tfl_api/issues
Author-email: Rob Aleck <mnbf9rca@users.noreply.github.com>
License: MIT
License-File: LICENSE
Keywords: pydantic,tfl,tfl-api,transport-for-london,unified-api
Classifier: Development Status :: 5 - Production/Stable
Classifier: Intended Audience :: Developers
Classifier: License :: OSI Approved :: MIT License
Classifier: Programming Language :: Python :: 3
Classifier: Programming Language :: Python :: 3.11
Classifier: Programming Language :: Python :: 3.12
Classifier: Programming Language :: Python :: 3.13
Classifier: Programming Language :: Python :: 3.14
Requires-Python: >=3.11
Requires-Dist: httpx<1.0,>=0.27.0
Requires-Dist: pydantic<3.0,>=2.8.2
Provides-Extra: requests
Requires-Dist: requests<3.0,>=2.32.3; extra == 'requests'
